Metadata-Version: 2.1
Name: lolipop
Version: 0.9.0
Summary: A set of scripts to cluster mutational trajectories into genotypes and infer lineage in the context of population evolution experiments.
Home-page: https://github.com/cdeitrick/lolipop
Author: chris deitrick
Author-email: chrisdeitrick1@gmail.com
License: MIT
Platform: UNKNOWN
Classifier: Programming Language :: Python :: 3
Classifier: License :: OSI Approved :: MIT License
Classifier: Operating System :: OS Independent
Provides: l
Provides: o
Provides: l
Provides: i
Provides: p
Provides: o
Provides: p
Requires-Dist: pandas (>=0.24.0)
Requires-Dist: loguru
Requires-Dist: scipy (>=1.3.0)
Requires-Dist: matplotlib (>=3.0.0)
Requires-Dist: graphviz
Requires-Dist: pygraphviz
Requires-Dist: seaborn
Requires-Dist: numpy (>=1.16.2)
Requires-Dist: xlrd
Requires-Dist: shapely (>=1.6.4)
Requires-Dist: tqdm
Provides-Extra: additional_support_for_parsing_files
Requires-Dist: beautifulsoup4 ; extra == 'additional_support_for_parsing_files'
Provides-Extra: generate_composite_graphs_from_the_genotye_lineage_timeseries_plots
Requires-Dist: pillow ; extra == 'generate_composite_graphs_from_the_genotye_lineage_timeseries_plots'
Provides-Extra: list_similar_annotations_when_selecting_genotypes
Requires-Dist: fuzzywuzzy ; extra == 'list_similar_annotations_when_selecting_genotypes'
Provides-Extra: to_run_tests
Requires-Dist: pytest ; extra == 'to_run_tests'
